odoo/addons/mrp_attachment_mgmt/README.rst
odoo/addons/mrp_attachment_mgmt/__init__.py
odoo/addons/mrp_attachment_mgmt/__manifest__.py
odoo/addons/mrp_attachment_mgmt/i18n/es.po
odoo/addons/mrp_attachment_mgmt/i18n/hr.po
odoo/addons/mrp_attachment_mgmt/i18n/hr_HR.po
odoo/addons/mrp_attachment_mgmt/i18n/it.po
odoo/addons/mrp_attachment_mgmt/i18n/mrp_attachment_mgmt.pot
odoo/addons/mrp_attachment_mgmt/models/__init__.py
odoo/addons/mrp_attachment_mgmt/models/mrp_bom.py
odoo/addons/mrp_attachment_mgmt/models/mrp_production.py
odoo/addons/mrp_attachment_mgmt/models/mrp_workorder.py
odoo/addons/mrp_attachment_mgmt/models/product.py
odoo/addons/mrp_attachment_mgmt/readme/CONFIGURE.md
odoo/addons/mrp_attachment_mgmt/readme/CONTRIBUTORS.md
odoo/addons/mrp_attachment_mgmt/readme/DESCRIPTION.md
odoo/addons/mrp_attachment_mgmt/readme/USAGE.md
odoo/addons/mrp_attachment_mgmt/static/description/icon.png
odoo/addons/mrp_attachment_mgmt/static/description/index.html
odoo/addons/mrp_attachment_mgmt/tests/__init__.py
odoo/addons/mrp_attachment_mgmt/tests/common.py
odoo/addons/mrp_attachment_mgmt/tests/test_mrp_attachment_mgmt.py
odoo/addons/mrp_attachment_mgmt/views/mrp_bom_view.xml
odoo/addons/mrp_attachment_mgmt/views/mrp_production_views.xml
odoo/addons/mrp_attachment_mgmt/views/product_views.xml
odoo/addons/mrp_attachment_mgmt/views/workorder_attachments_views.xml
odoo_addon_mrp_attachment_mgmt-18.0.1.0.0.4.dist-info/METADATA
odoo_addon_mrp_attachment_mgmt-18.0.1.0.0.4.dist-info/WHEEL
odoo_addon_mrp_attachment_mgmt-18.0.1.0.0.4.dist-info/top_level.txt
odoo_addon_mrp_attachment_mgmt-18.0.1.0.0.4.dist-info/RECORD
